{
  "grid_id": 143,
  "grid": [
    [
      "G",
      "B",
      "B",
      "B"
    ],
    [
      "R",
      "R",
      "R",
      "R"
    ],
    [
      "B",
      "R",
      "B",
      "R"
    ],
    [
      "B",
      "B",
      "R",
      "G"
    ]
  ],
  "game_id": "grid_143_20250918_180722",
  "timestamp": "20250918_180722",
  "bucket": "Needy Player (Blue)",
  "sub_stratum": "NP-Blue (Need=2)",
  "config": {
    "pay4partner": false,
    "contract_type": "tile_with_judge_implementation",
    "with_context": true,
    "with_message_history": true,
    "fog_of_war": [
      false,
      false
    ]
  },
  "grid_metrics": {
    "b_min_trades_efficient_path": 2,
    "b_max_trades_efficient_path": 3,
    "r_min_trades_efficient_path": 0,
    "r_max_trades_efficient_path": 3,
    "trade_asymmetry": 2
  }
}